{
  "Info": {
    "Class": "clsDbForm",
    "Description": "PF_Tab Print Settings"
  },
  "Items": {
    "Printer": {
      "Orientation": "Landscape",
      "PaperSize": "A4"
    },
    "Margins": {
      "LeftMargin": 0.3938,
      "TopMargin": 0.3938,
      "RightMargin": 0.3938,
      "BotMargin": 0.3938,
      "DataOnly": false,
      "Width": 5,
      "Height": 3,
      "DefaultSize": true,
      "Columns": 1,
      "ColumnSpacing": 0.25,
      "RowSpacing": 0,
      "ItemLayout": "Horizontal Columns",
      "FastPrint": 1,
      "Datasheet": 1
    }
  }
}
